src/__init__.py
src/uniqcharspac/__init__.py
src/uniqcharspac/main.py
src/uniqcharspac/app/__init__.py
src/uniqcharspac/app/app.py
src/uniqcharspac/utils/__init__.py
src/uniqcharspac/utils/exceptions.py
src/uniqcharspac/utils/functions.py
tests/__init__.py
uniqcharspac-1.2.dist-info/LICENSE
uniqcharspac-1.2.dist-info/METADATA
uniqcharspac-1.2.dist-info/WHEEL
uniqcharspac-1.2.dist-info/entry_points.txt
uniqcharspac-1.2.dist-info/top_level.txt
uniqcharspac-1.2.dist-info/RECORD
